npy/__init__.py
npy/constants.py
npy/errors.py
npy/ns.py
npy/calc/__init__.py
npy/calc/check.py
npy/calc/miscs.py
npy/data/__init__.py
npy/data/miscs.py
npy/ex/__init__.py
npy/ex/imagenet.py
npy/ex/mnist.py
npy/ex/example_images/ostrich.png
npy/ex/example_images/saxophone.png
npy/ex/example_images/mnist/0.png
npy/ex/example_images/mnist/1.png
npy/ex/example_images/mnist/2.png
npy/ex/example_images/mnist/3.png
npy/ex/example_images/mnist/4.png
npy/ex/example_images/mnist/5.png
npy/ex/example_images/mnist/6.png
npy/ex/example_images/mnist/7.png
npy/ex/example_images/mnist/8.png
npy/ex/example_images/mnist/9.png
npy/files/__init__.py
npy/files/async_writers.py
npy/files/io.py
npy/files/path.py
npy/image/__init__.py
npy/image/augment.py
npy/image/bbox.py
npy/image/decorators.py
npy/image/miscs.py
npy/image/modify.py
npy/image/plot.py
npy/image/transform.py
npy/image/basic/__init__.py
npy/image/basic/dtype_range.py
npy/image/basic/formats.py
npy/image/basic/shapes.py
npy/image/constants/__init__.py
npy/image/constants/dtype_range.py
npy/image/constants/formats.py
npy/log/__init__.py
npy/log/loggers.py
npy/log/setters.py
npy/log/telegram_handler.py
npy/tools/__init__.py
npy/tools/bash_commands.py
npy/tools/http.py
npy/tools/intrinsic_dimension.py
npy/tools/parallel.py
npy/tools/short_hands.py
npy/tools/track.py
npy/tools/tsne.py
npy/tools/vec.py
npy/tools/multirank/__init__.py
npy/tools/multirank/analysis.py
npy/tools/multirank/basic.py
npy/tools/multirank/modify.py
npy/tools/multirank/recursive.py
npy/utils/__init__.py
npy/utils/utils_dataframe.py
npy/utils/utils_decorator.py
npy/utils/utils_exp.py
npy/utils/utils_info.py
npy/utils/utils_mask.py
npy/utils/utils_misc.py
npy/utils/utils_profiler.py
npy/utils/utils_task_context.py
npy/utils/datastructure/__init__.py
npy/utils/datastructure/d_of.py
npy/utils/datastructure/dashboard.py
npy/utils/datastructure/meter.py
npy/utils/datastructure/storage.py
npy/utils/multirank/__init__.py
npy/utils/multirank/basic.py
nuclear_python-0.15.15.dist-info/METADATA
nuclear_python-0.15.15.dist-info/WHEEL
nuclear_python-0.15.15.dist-info/top_level.txt
nuclear_python-0.15.15.dist-info/RECORD
