Metadata-Version: 2.1
Name: nuclear-python
Version: 0.15.15
Summary: Python helpers
Home-page: https://github.com/nuclearboy95/nuclear-python
Author: Jihun Yi
Author-email: t080205@gmail.com
License: MIT
Platform: UNKNOWN
Requires-Dist: coloredlogs (>=10.0)
Requires-Dist: tabulate (>=0.8)
Requires-Dist: tqdm (>=4.26)
Requires-Dist: numpy (>=1.14)
Requires-Dist: scikit-learn (>=0.17.1)
Requires-Dist: scipy (>=1.0.0)
Requires-Dist: matplotlib (>=3.0.0)
Requires-Dist: Pillow (>=5.3.0)
Requires-Dist: pandas
Requires-Dist: imageio
Requires-Dist: opencv-python
Requires-Dist: pyyaml
Requires-Dist: requests
